{
    "asset": {
        "format": "jpeg",
        "id": "f9a8bd78a00c626cde6eeaaf0dd4bf23",
        "name": "Aircraft%20Carrier_93.jpeg",
        "path": "file:C:/Users/tobia/source/repos/H5/ThePirateHay/dataset/train/trainset/Aircraft%20Carrier_93.jpeg",
        "size": {
            "width": 600,
            "height": 416
        },
        "state": 2,
        "type": 1
    },
    "regions": [
        {
            "id": "XbXtZVEsYT",
            "type": "POLYGON",
            "tags": [
                "Carrier"
            ],
            "boundingBox": {
                "height": 374.92163009404385,
                "width": 573.9130434782609,
                "left": 2.511888586956522,
                "top": 39.774294670846395
            },
            "points": [
                {
                    "x": 56.31623641304348,
                    "y": 414.69592476489026
                },
                {
                    "x": 49.14232336956522,
                    "y": 388.9404388714733
                },
                {
                    "x": 33.1640625,
                    "y": 366.1191222570533
                },
                {
                    "x": 12.294497282608695,
                    "y": 344.60188087774293
                },
                {
                    "x": 2.511888586956522,
                    "y": 328.30094043887146
                },
                {
                    "x": 58.272758152173914,
                    "y": 325.0407523510972
                },
                {
                    "x": 97.72927989130434,
                    "y": 327.6489028213166
                },
                {
                    "x": 107.83797554347827,
                    "y": 309.0658307210031
                },
                {
                    "x": 120.22927989130434,
                    "y": 281.3542319749216
                },
                {
                    "x": 135.5553668478261,
                    "y": 264.0752351097179
                },
                {
                    "x": 139.14232336956522,
                    "y": 220.38871473354232
                },
                {
                    "x": 147.62058423913044,
                    "y": 190.72100313479623
                },
                {
                    "x": 159.68580163043478,
                    "y": 160.40125391849529
                },
                {
                    "x": 159.0336277173913,
                    "y": 119.97492163009403
                },
                {
                    "x": 167.51188858695653,
                    "y": 98.78369905956112
                },
                {
                    "x": 176.31623641304347,
                    "y": 65.20376175548589
                },
                {
                    "x": 180.88145380434784,
                    "y": 39.774294670846395
                },
                {
                    "x": 188.38145380434784,
                    "y": 51.18495297805642
                },
                {
                    "x": 189.0336277173913,
                    "y": 84.11285266457679
                },
                {
                    "x": 186.09884510869566,
                    "y": 111.8244514106583
                },
                {
                    "x": 203.38145380434784,
                    "y": 117.69278996865204
                },
                {
                    "x": 207.9466711956522,
                    "y": 143.7742946708464
                },
                {
                    "x": 185.7727581521739,
                    "y": 161.3793103448276
                },
                {
                    "x": 181.85971467391303,
                    "y": 210.6081504702194
                },
                {
                    "x": 208.9249320652174,
                    "y": 218.1065830721003
                },
                {
                    "x": 222.2944972826087,
                    "y": 242.23197492163007
                },
                {
                    "x": 228.1640625,
                    "y": 315.2601880877743
                },
                {
                    "x": 552.2944972826087,
                    "y": 310.36990595611286
                },
                {
                    "x": 572.5118885869565,
                    "y": 334.16927899686516
                },
                {
                    "x": 576.4249320652174,
                    "y": 347.5360501567398
                },
                {
                    "x": 555.2292798913044,
                    "y": 355.6865203761755
                },
                {
                    "x": 545.4466711956521,
                    "y": 413.717868338558
                }
            ]
        }
    ],
    "version": "2.2.0"
}