<annotation>
	<folder>train</folder>
	<filename>35.jpeg</filename>
	<path>C:\Users\tobia\source\repos\H5\tf2\models\research\object_detection\images\train\35.jpeg</path>
	<source>
		<database>Unknown</database>
	</source>
	<size>
		<width>1920</width>
		<height>1080</height>
		<depth>3</depth>
	</size>
	<segmented>0</segmented>
	<object>
		<name>Bulker</name>
		<pose>Unspecified</pose>
		<truncated>0</truncated>
		<difficult>0</difficult>
		<bndbox>
			<xmin>241</xmin>
			<ymin>230</ymin>
			<xmax>1655</xmax>
			<ymax>993</ymax>
		</bndbox>
	</object>
</annotation>
