<annotation>
	<folder>train</folder>
	<filename>86.jpeg</filename>
	<path>C:\Users\tobia\source\repos\H5\tf2\models\research\object_detection\images\train\86.jpeg</path>
	<source>
		<database>Unknown</database>
	</source>
	<size>
		<width>600</width>
		<height>416</height>
		<depth>1</depth>
	</size>
	<segmented>0</segmented>
	<object>
		<name>Destroyer</name>
		<pose>Unspecified</pose>
		<truncated>0</truncated>
		<difficult>0</difficult>
		<bndbox>
			<xmin>8</xmin>
			<ymin>26</ymin>
			<xmax>597</xmax>
			<ymax>394</ymax>
		</bndbox>
	</object>
</annotation>
